fixit/__init__.py
fixit/_version.py
fixit/py.typed
fixit/rule_lint_engine.py
fixit/cli/__init__.py
fixit/cli/add_new_rule.py
fixit/cli/apply_fix.py
fixit/cli/args.py
fixit/cli/formatter.py
fixit/cli/full_repo_metadata.py
fixit/cli/init_config.py
fixit/cli/insert_suppressions.py
fixit/cli/main.py
fixit/cli/run_rules.py
fixit/cli/utils.py
fixit/cli/tests/__init__.py
fixit/cli/tests/test_args.py
fixit/cli/tests/test_formatter.py
fixit/cli/tests/test_ipc.py
fixit/cli/tests/test_lint_opts.py
fixit/cli/tests/test_type_inference.py
fixit/common/__init__.py
fixit/common/autofix.py
fixit/common/base.py
fixit/common/comments.py
fixit/common/config.py
fixit/common/config.schema.json
fixit/common/document.py
fixit/common/flake8_compat.py
fixit/common/full_repo_metadata.py
fixit/common/generate_pyre_fixtures.py
fixit/common/ignores.py
fixit/common/insert_suppressions.py
fixit/common/line_mapping.py
fixit/common/pseudo_rule.py
fixit/common/report.py
fixit/common/testing.py
fixit/common/unused_suppressions.py
fixit/common/utils.py
fixit/common/cli/__init__.py
fixit/common/cli/args.py
fixit/common/cli/formatter.py
fixit/common/tests/__init__.py
fixit/common/tests/test_autofix.py
fixit/common/tests/test_comments.py
fixit/common/tests/test_config.py
fixit/common/tests/test_flake8_compat.py
fixit/common/tests/test_full_repo_metadata.py
fixit/common/tests/test_get_code.py
fixit/common/tests/test_ignores.py
fixit/common/tests/test_imports.py
fixit/common/tests/test_insert_suppressions.py
fixit/common/tests/test_line_mapping.py
fixit/common/tests/test_pseudo_rule.py
fixit/common/tests/test_report.py
fixit/common/tests/test_unused_suppressions.py
fixit/common/tests/dummy_package/__init__.py
fixit/common/tests/dummy_package/dummy_1.py
fixit/common/tests/dummy_package/dummy_2.py
fixit/common/tests/dummy_package/dummy_subpackage/__init__.py
fixit/common/tests/dummy_package/dummy_subpackage/dummy.py
fixit/rules/__init__.py
fixit/rules/add_file_header.py
fixit/rules/avoid_or_in_except.py
fixit1-0.1.4.dist-info/LICENSE
fixit1-0.1.4.dist-info/METADATA
fixit1-0.1.4.dist-info/WHEEL
fixit1-0.1.4.dist-info/entry_points.txt
fixit1-0.1.4.dist-info/top_level.txt
fixit1-0.1.4.dist-info/RECORD
