Metadata-Version: 2.1
Name: fixit1
Version: 0.1.4
Summary: A lint framework that writes better Python code for you.
Home-page: https://github.com/Instagram/Fixit
License: MIT
Classifier: License :: OSI Approved :: MIT License
Classifier: Topic :: Software Development :: Libraries
Classifier: Topic :: Software Development :: Quality Assurance
Classifier: Programming Language :: Python :: 3.6
Classifier: Programming Language :: Python :: 3.7
Classifier: Programming Language :: Python :: 3.8
Classifier: Typing :: Typed
Requires-Python: >=3.6
License-File: LICENSE
Requires-Dist: flake8 (>=3.8.1)
Requires-Dist: libcst (>=0.3.18)
Requires-Dist: pyyaml (>=5.2)
Requires-Dist: jsonschema (>=3.2.0)
Requires-Dist: importlib-resources (>=5.1.2)
Provides-Extra: dev
Requires-Dist: black (>=19.10b0) ; extra == 'dev'
Requires-Dist: codecov (>=2.0.15) ; extra == 'dev'
Requires-Dist: coverage (>=4.5.4) ; extra == 'dev'
Requires-Dist: isort (>=4.3.20) ; extra == 'dev'
Requires-Dist: jupyter (>=1.0.0) ; extra == 'dev'
Requires-Dist: nbsphinx (>=0.7.1) ; extra == 'dev'
Requires-Dist: pyre-check (==0.0.41) ; extra == 'dev'
Requires-Dist: sphinx-rtd-theme (>=0.5.0) ; extra == 'dev'
Requires-Dist: prompt-toolkit (>=2.0.9) ; extra == 'dev'
Requires-Dist: tox (>=3.14.5) ; extra == 'dev'
Requires-Dist: diff-cover (>=3.0.1) ; extra == 'dev'
